{
  "index": {
    "icon": "home",
    "title": "Angular Docs",
    "subtitle": "TypeScript",
    "menuTitle": "Docs Home",
    "banner": "最新のAngularリリースは<b> 4.0 </b>です。 最新の<a href='guide/change-log.html' title='Documentation change log'>ドキュメントの最新情報</a>をご覧ください。 拡張機能のための<a href='https://github.com/angular/angular/blob/master/CHANGELOG.md' target='_blank' title='Angular Product Changes'>角度変更ログ</a>をご覧ください。 Angular自体の変更を修正し、修正します。 Angular v2ドキュメントをお探しの場合は、<a href='https://v2.angular.io' title='Angular v2 docs archive'> v2.angular.io </a>にあります。"
  },

  "quickstart": {
    "icon": "query-builder",
    "title": "Quickstart",
    "subtitle": "TypeScript",
    "banner": "Angular の基礎を簡単に見てください。"
  },

  "cli-quickstart": {
    "icon": "query-builder",
    "title": "CLI Quickstart",
    "subtitle": "TypeScript",
    "banner": "CLIツールを使用すると、Angularアプリケーションを迅速に構築できます。"
  },

  "tutorial": {
    "icon": "list",
    "title": "Tutorial",
    "subtitle": "TypeScript"
  },

  "guide": {
    "icon": "list",
    "title": "Guide",
    "subtitle": "TypeScript"
  },

  "cookbook": {
    "icon": "list",
    "title": "Cookbook",
    "subtitle": "TypeScript",
    "banner": "共通の実装上の課題を解決する方法です。"
  },

  "api/": {
    "icon": "book",
    "title": "API Reference",
    "subtitle": "TypeScript",
    "reference": true
  },

  "cheatsheet": {
    "title": "Cheat Sheet",
    "subtitle": "TypeScript",
    "reference": false
  },

  "glossary": {
    "title": "Glossary",
    "subtitle": "TypeScript",
    "intro": "Brief definitions of the most important words in the Angular vocabulary",
    "reference": false
  },

  "resources": {
    "icon": "play-circle-fill",
    "title": "Angular Resources",
    "subtitle": "TypeScript",
    "resources": true
  },

  "help": {
    "icon": "chat",
    "title": "Help & Support",
    "subtitle": "From our team & community",
    "resources": true
  },

  "styleguide": {
    "title": "Docs Style Guide",
    "subtitle": "TypeScript",
    "intro": "Design & Layout Patterns For Documentation"
  }
}
